{"Name":"Group 2","Teams":[{"Name":"The Netherlands","Rating":0.9},{"Name":"Soviet Union","Rating":0.9},{"Name":"Republic of Ireland","Rating":0.2},{"Name":"England","Rating":0.6}],"Matches":[{"Team1":{"Name":"The Netherlands","Rating":0.9},"Team2":{"Name":"Soviet Union","Rating":0.9},"GoalsTeam1":2,"GoalsTeam2":2},{"Team1":{"Name":"Republic of Ireland","Rating":0.2},"Team2":{"Name":"The Netherlands","Rating":0.9},"GoalsTeam1":2,"GoalsTeam2":2},{"Team1":{"Name":"The Netherlands","Rating":0.9},"Team2":{"Name":"England","Rating":0.6},"GoalsTeam1":2,"GoalsTeam2":2},{"Team1":{"Name":"Republic of Ireland","Rating":0.2},"Team2":{"Name":"Soviet Union","Rating":0.9},"GoalsTeam1":2,"GoalsTeam2":2},{"Team1":{"Name":"Soviet Union","Rating":0.9},"Team2":{"Name":"England","Rating":0.6},"GoalsTeam1":2,"GoalsTeam2":2},{"Team1":{"Name":"England","Rating":0.6},"Team2":{"Name":"Republic of Ireland","Rating":0.2},"GoalsTeam1":2,"GoalsTeam2":2}],"Results":[{"Team":{"Name":"The Netherlands","Rating":0.9},"Position":0,"Played":3,"Won":0,"Draw":3,"Lost":0,"GoalsFor":6,"GoalsAgainst":6,"GoalDifference":0,"Points":3,"IsTie":false,"GoalDifferenceString":"0"},{"Team":{"Name":"Soviet Union","Rating":0.9},"Position":0,"Played":3,"Won":0,"Draw":3,"Lost":0,"GoalsFor":6,"GoalsAgainst":6,"GoalDifference":0,"Points":3,"IsTie":false,"GoalDifferenceString":"0"},{"Team":{"Name":"Republic of Ireland","Rating":0.2},"Position":0,"Played":3,"Won":0,"Draw":3,"Lost":0,"GoalsFor":6,"GoalsAgainst":6,"GoalDifference":0,"Points":3,"IsTie":false,"GoalDifferenceString":"0"},{"Team":{"Name":"England","Rating":0.6},"Position":0,"Played":3,"Won":0,"Draw":3,"Lost":0,"GoalsFor":6,"GoalsAgainst":6,"GoalDifference":0,"Points":3,"IsTie":false,"GoalDifferenceString":"0"}]}
